README.md
setup.py
debug_error_logging/__init__.py
debug_error_logging/models.py
debug_error_logging/tests.py
debug_error_logging/__pycache__/__init__.cpython-37.pyc
debug_error_logging/__pycache__/models.cpython-37.pyc
debug_error_logging/__pycache__/tests.cpython-37.pyc
django_debug_error_logging.egg-info/PKG-INFO
django_debug_error_logging.egg-info/SOURCES.txt
django_debug_error_logging.egg-info/dependency_links.txt
django_debug_error_logging.egg-info/top_level.txt