Metadata-Version: 1.0
Name: django-debug-error-logging
Version: 2.1.1
Summary: Enable error logging in Django when DEBUG = True
Home-page: http://github.com/brightinteractive/django-debug-error-logging/
Author: Bright Interactive
Author-email: francis@bright-interactive.co.uk
License: BSD
Platform: UNKNOWN
